CHANGES.rst
MANIFEST.in
README.rst
setup.py
forms2/__init__.py
forms2/access.py
forms2/sqlalchemy.py
forms2.egg-info/PKG-INFO
forms2.egg-info/SOURCES.txt
forms2.egg-info/dependency_links.txt
forms2.egg-info/requires.txt
forms2.egg-info/top_level.txt