Metadata-Version: 1.0
Name: forms2
Version: 1.1.0
Summary: Extra features for Django Forms
Home-page: UNKNOWN
Author: Paylogic International
Author-email: developers@paylogic.com
License: MIT
Keywords: django forms extensions sqlalchemy acl
Platform: UNKNOWN
